dbt_coves/__init__.py
dbt_coves/config/__init__.py
dbt_coves/config/config.py
dbt_coves/core/__init__.py
dbt_coves/core/exceptions.py
dbt_coves/core/main.py
dbt_coves/tasks/__init__.py
dbt_coves/tasks/base.py
dbt_coves/tasks/blue_green/__init__.py
dbt_coves/tasks/blue_green/clone_db.py
dbt_coves/tasks/blue_green/main.py
dbt_coves/tasks/data_sync/__init__.py
dbt_coves/tasks/data_sync/base.py
dbt_coves/tasks/data_sync/main.py
dbt_coves/tasks/data_sync/redshift.py
dbt_coves/tasks/data_sync/snowflake.py
dbt_coves/tasks/data_sync/sql_database/README.md
dbt_coves/tasks/data_sync/sql_database/__init__.py
dbt_coves/tasks/data_sync/sql_database/helpers.py
dbt_coves/tasks/data_sync/sql_database/schema_types.py
dbt_coves/tasks/dbt/main.py
dbt_coves/tasks/extract/__init__.py
dbt_coves/tasks/extract/airbyte.py
dbt_coves/tasks/extract/base.py
dbt_coves/tasks/extract/fivetran.py
dbt_coves/tasks/extract/main.py
dbt_coves/tasks/generate/__init__.py
dbt_coves/tasks/generate/airflow_dags.py
dbt_coves/tasks/generate/airflow_generators/__init__.py
dbt_coves/tasks/generate/airflow_generators/airbyte.py
dbt_coves/tasks/generate/airflow_generators/base.py
dbt_coves/tasks/generate/airflow_generators/fivetran.py
dbt_coves/tasks/generate/base.py
dbt_coves/tasks/generate/docs.py
dbt_coves/tasks/generate/main.py
dbt_coves/tasks/generate/metadata.py
dbt_coves/tasks/generate/properties.py
dbt_coves/tasks/generate/sources.py
dbt_coves/tasks/generate/templates.py
dbt_coves/tasks/load/__init__.py
dbt_coves/tasks/load/airbyte.py
dbt_coves/tasks/load/base.py
dbt_coves/tasks/load/fivetran.py
dbt_coves/tasks/load/main.py
dbt_coves/tasks/setup/__init__.py
dbt_coves/tasks/setup/main.py
dbt_coves/tasks/setup/utils.py
dbt_coves/templates/model_props.yml
dbt_coves/templates/source_props.yml
dbt_coves/templates/staging_model.sql
dbt_coves/templates/staging_model_props.yml
dbt_coves/ui/__init__.py
dbt_coves/ui/traceback.py
dbt_coves/utils/__init__.py
dbt_coves/utils/api_caller.py
dbt_coves/utils/flags.py
dbt_coves-1.10.7.dist-info/METADATA
dbt_coves-1.10.7.dist-info/WHEEL
dbt_coves-1.10.7.dist-info/entry_points.txt
dbt_coves-1.10.7.dist-info/licenses/LICENSE
dbt_coves-1.10.7.dist-info/RECORD
