Metadata-Version: 2.4
Name: dbt_coves
Version: 1.10.7
Summary: CLI tool for dbt users adopting analytics engineering best practices.
License: Apache 2.0
License-File: LICENSE
Keywords: data engineering,analytics engineering,dbt,ETL,data modelling
Author: Datacoves
Author-email: hello@datacoves.com
Requires-Python: >=3.9,<3.13
Classifier: Development Status :: 5 - Production/Stable
Classifier: Intended Audience :: Information Technology
Classifier: License :: OSI Approved :: Apache Software License
Classifier: License :: Other/Proprietary License
Classifier: Programming Language :: Python :: 3
Classifier: Programming Language :: Python :: 3.9
Classifier: Programming Language :: Python :: 3.10
Classifier: Programming Language :: Python :: 3.11
Classifier: Programming Language :: Python :: 3.12
Classifier: Programming Language :: Python :: 3.7
Classifier: Programming Language :: Python :: 3.8
Classifier: Topic :: Software Development :: Build Tools
Classifier: Topic :: Software Development :: Code Generators
Requires-Dist: Jinja2 (>2.11.2)
Requires-Dist: PyYAML (>=5.4.1)
Requires-Dist: black (>=24,<25)
Requires-Dist: bumpversion (>=0.6.0,<0.7.0)
Requires-Dist: click (>=8.0.3,<9.0.0)
Requires-Dist: copier (>=9.0.0)
Requires-Dist: db-dtypes (>=1.0.5,<2.0.0)
Requires-Dist: dbt-core (>=1.1,<1.11)
Requires-Dist: dlt[redshift] (>=1.0)
Requires-Dist: enlighten (>=1.12.4,<2.0.0)
Requires-Dist: gitpython (>=3.1.31,<4.0.0)
Requires-Dist: isort (>=5.12.0,<6.0.0)
Requires-Dist: jinja2-env (>=0.1.3,<0.2.0)
Requires-Dist: luddite (>=1.0.1,<2.0.0)
Requires-Dist: mixpanel (>=4.10.0,<5.0.0)
Requires-Dist: packaging (>=20.8)
Requires-Dist: pretty-errors (>=1.2.19,<2.0.0)
Requires-Dist: prompt-toolkit (==3.0.51)
Requires-Dist: psycopg2-binary (>=2.9.9,<3.0.0)
Requires-Dist: pydantic (>=1.8)
Requires-Dist: pyfiglet (>=0.8.post1,<0.9)
Requires-Dist: python-slugify (<9.0.0)
Requires-Dist: pyyaml-include (<2.0)
Requires-Dist: questionary (==2.1.1)
Requires-Dist: rich (>=10.4)
Requires-Dist: ruamel-yaml (>=0.17.21,<0.18.0)
Requires-Dist: snowflake-connector-python (>=3.12.1,<4.3)
Requires-Dist: sqlalchemy (>=1.4,<2.0)
Requires-Dist: typing_extensions (>=4.0,<5.0) ; python_version >= "3.7" and python_version < "4.0"
Requires-Dist: yamlloader (>=1.0.0,<2.0.0)
Project-URL: Documentation, https://github.com/datacoves/dbt-coves/blob/main/README.md
Project-URL: Homepage, https://datacoves.com
Project-URL: Repository, https://github.com/datacoves/dbt-coves
